ewoxcore/cache/cache.py
ewoxcore/cache/cache_provider.py
ewoxcore/cache/icache_local_provider.py
ewoxcore/cache/icache_provider.py
ewoxcore/cache/timer_ext.py
ewoxcore/client/graphql_client.py
ewoxcore/client/http_client.py
ewoxcore/client/list_model.py
ewoxcore/client/paging_args.py
ewoxcore/client/paging_model.py
ewoxcore/client/status_code.py
ewoxcore/client/timeout_adapter.py
ewoxcore/collections/fifo_queue.py
ewoxcore/collections/stack.py
ewoxcore/collections/stack_util.py
ewoxcore/configuration/configuration.py
ewoxcore/configuration/configuration_builder.py
ewoxcore/configuration/interfaces/iconfiguration_builder.py
ewoxcore/constants/global_key.py
ewoxcore/constants/interval_type.py
ewoxcore/constants/server_env.py
ewoxcore/constants/time_period_name.py
ewoxcore/constants/week_day.py
ewoxcore/decorators/serializable.py
ewoxcore/ext/switch.py
ewoxcore/items/.DS_Store
ewoxcore/items/__init__.py
ewoxcore/items/adapters/json_item_adapter.py
ewoxcore/items/adapters/property_item_adapter.py
ewoxcore/items/interchange/interchange_property.py
ewoxcore/items/item.py
ewoxcore/items/item_base.py
ewoxcore/items/item_constants.py
ewoxcore/items/item_converter.py
ewoxcore/items/item_provider.py
ewoxcore/items/item_value_serializer.py
ewoxcore/items/key_value_pair.py
ewoxcore/items/property_item.py
ewoxcore/items/property_selector.py
ewoxcore/localize/ilocalizer.py
ewoxcore/localize/localize_provider.py
ewoxcore/math/__init__.py
ewoxcore/math/point.py
ewoxcore/math/size.py
ewoxcore/memory/imemory_handle.py
ewoxcore/message/imessage_consumer.py
ewoxcore/message/message_adapter.py
ewoxcore/message/message_args.py
ewoxcore/module/lazy_loader.py
ewoxcore/module/module_manager.py
ewoxcore/monitoring/constants/log_level.py
ewoxcore/monitoring/ilogger.py
ewoxcore/monitoring/logging_factory.py
ewoxcore/monitoring/models/log_event.py
ewoxcore/monitoring/models/log_events.py
ewoxcore/monitoring/monitoring_event.py
ewoxcore/monitoring/monitoring_event_name.py
ewoxcore-1.6.27.dist-info/METADATA
ewoxcore-1.6.27.dist-info/WHEEL
ewoxcore-1.6.27.dist-info/licenses/LICENSE
ewoxcore-1.6.27.dist-info/RECORD
