Metadata-Version: 2.4
Name: ewoxcore
Version: 1.6.27
Summary: 
License-File: LICENSE
Author: Martin Leo Prüss
Author-email: mleopruss@gmail.com
Requires-Python: >=3.9.9,<4.0.0
Classifier: Programming Language :: Python :: 3
Classifier: Programming Language :: Python :: 3.10
Classifier: Programming Language :: Python :: 3.11
Classifier: Programming Language :: Python :: 3.12
Classifier: Programming Language :: Python :: 3.13
Classifier: Programming Language :: Python :: 3.14
Requires-Dist: cryptography (>=42.0.7,<43.0.0)
Requires-Dist: jose (>=1.0.0,<2.0.0)
Requires-Dist: jsonpickle (>=4.1.1,<5.0.0)
Requires-Dist: lagom (>=2.6.0,<3.0.0)
Requires-Dist: pandas (>=2.2.2,<3.0.0)
Requires-Dist: python-dateutil (>=2.8.2,<3.0.0)
Requires-Dist: python-i18n (>=0.3.9,<0.4.0)
Requires-Dist: python-jose[cryptography] (>=3.3.0,<4.0.0)
Requires-Dist: requests (>=2.27.1,<3.0.0)
Requires-Dist: requests-toolbelt (>=1.0.0,<2.0.0)
Requires-Dist: shortuuid (>=1.0.1,<2.0.0)
Requires-Dist: sortedcontainers (>=2.4.0,<3.0.0)
Requires-Dist: urllib3 (>=1.26.8,<2.0.0)
Requires-Dist: validators (>=0.35.0,<0.36.0)
